google_cloud_utils/__init__.py
google_cloud_utils/google_cloud_bigquery.py
google_cloud_utils/google_cloud_credentials.py
google_cloud_utils/google_cloud_logger.py
google_cloud_utils-0.1.0.dist-info/LICENSE
google_cloud_utils-0.1.0.dist-info/METADATA
google_cloud_utils-0.1.0.dist-info/WHEEL
google_cloud_utils-0.1.0.dist-info/top_level.txt
google_cloud_utils-0.1.0.dist-info/RECORD
