Metadata-Version: 2.1
Name: google-cloud-utils
Version: 0.1.0
Summary: Google cloud utilities package
Home-page: https://bitbucket.org/extremize/common-packages-public/src/main/
Author: Jheel Patel
Author-email: jheelpatelscientist@gmail.com
Project-URL: repository, https://bitbucket.org/extremize/common-packages-public/src/main/
Classifier: Programming Language :: Python :: 3
Classifier: License :: OSI Approved :: MIT License
Classifier: Operating System :: OS Independent
Requires-Python: >=3.6
License-File: LICENSE
Requires-Dist: google-auth (==2.16.0)
Requires-Dist: google-cloud-logging (==3.4.0)
Requires-Dist: google-cloud-bigquery (==3.4.2)
Requires-Dist: bigquery-schema-generator (==1.5.1)
Requires-Dist: python-dotenv (==0.21.1)
